{
	"configurations" : 
	[
		{
			"directories" : 
			[
				{
					"build" : ".",
					"hasInstallRule" : true,
					"minimumCMakeVersion" : 
					{
						"string" : "3.5"
					},
					"projectIndex" : 0,
					"source" : ".",
					"targetIndexes" : 
					[
						0
					]
				}
			],
			"name" : "Debug",
			"projects" : 
			[
				{
					"directoryIndexes" : 
					[
						0
					],
					"name" : "common_prefix",
					"targetIndexes" : 
					[
						0
					]
				}
			],
			"targets" : 
			[
				{
					"directoryIndex" : 0,
					"id" : "common_prefix::@6890427a1f51a3e7e1df",
					"jsonFile" : "target-common_prefix-Debug-6c011b90fdbf67f5f15a.json",
					"name" : "common_prefix",
					"projectIndex" : 0
				}
			]
		}
	],
	"kind" : "codemodel",
	"paths" : 
	{
		"build" : "/home/matu/cpp/build-common_prefix-Desktop_Qt_5_15_2_GCC_64bit-Debug",
		"source" : "/home/matu/cpp/common_prefix"
	},
	"version" : 
	{
		"major" : 2,
		"minor" : 0
	}
}
